xi/__init__.py
xi/sdk/__init__.py
xi/sdk/resellers/__init__.py
xi/sdk/resellers/api_client.py
xi/sdk/resellers/api_response.py
xi/sdk/resellers/configuration.py
xi/sdk/resellers/exceptions.py
xi/sdk/resellers/py.typed
xi/sdk/resellers/rest.py
xi/sdk/resellers/api/__init__.py
xi/sdk/resellers/api/accesstoken_api.py
xi/sdk/resellers/api/deals_api.py
xi/sdk/resellers/api/freight_estimate_api.py
xi/sdk/resellers/api/invoices_api.py
xi/sdk/resellers/api/order_status_api.py
xi/sdk/resellers/api/orders_api.py
xi/sdk/resellers/api/product_catalog_api.py
xi/sdk/resellers/api/quotes_api.py
xi/sdk/resellers/api/renewals_api.py
xi/sdk/resellers/api/returns_api.py
xi/sdk/resellers/api/stock_update_api.py
xi/sdk/resellers/models/__init__.py
xi/sdk/resellers/models/accesstoken_response.py
xi/sdk/resellers/models/availability_async_notification_request.py
xi/sdk/resellers/models/availability_async_notification_request_resource_inner.py
xi/sdk/resellers/models/availability_async_notification_request_resource_inner_links_inner.py
xi/sdk/resellers/models/deals_details_response.py
xi/sdk/resellers/models/deals_details_response_products_inner.py
xi/sdk/resellers/models/deals_search_response.py
xi/sdk/resellers/models/deals_search_response_deals_inner.py
xi/sdk/resellers/models/error.py
xi/sdk/resellers/models/error_response.py
xi/sdk/resellers/models/error_response_dto.py
xi/sdk/resellers/models/error_response_errors_inner.py
xi/sdk/resellers/models/error_response_errors_inner_fields_inner.py
xi/sdk/resellers/models/fields.py
xi/sdk/resellers/models/freight_request.py
xi/sdk/resellers/models/freight_request_lines_inner.py
xi/sdk/resellers/models/freight_request_ship_to_address.py
xi/sdk/resellers/models/freight_response.py
xi/sdk/resellers/models/freight_response_freight_estimate_response.py
xi/sdk/resellers/models/freight_response_freight_estimate_response_distribution_inner.py
xi/sdk/resellers/models/freight_response_freight_estimate_response_distribution_inner_carrier_list_inner.py
xi_sdk_resellers-1.3.0.dist-info/licenses/LICENCE
xi_sdk_resellers-1.3.0.dist-info/METADATA
xi_sdk_resellers-1.3.0.dist-info/WHEEL
xi_sdk_resellers-1.3.0.dist-info/top_level.txt
xi_sdk_resellers-1.3.0.dist-info/RECORD
