Metadata-Version: 2.4
Name: xi.sdk.resellers
Version: 1.3.0
Summary: Ingram Micro - Xvantage Integration (XI) Python Server-side SDK.
Home-page: https://github.com/ingrammicro-xvantage/xi-sdk-resellers-python
Author: Ingram Micro Xvantage Integration(XI)
Author-email: "Ingram Micro Xvantage Integration(XI)" <xi_support@ingrammicro.com>
License: MIT
Project-URL: repository, https://github.com/ingrammicro-xvantage/xi-sdk-resellers-python
Project-URL: homepage, https://github.com/ingrammicro-xvantage/xi-sdk-resellers-python
Project-URL: download, https://github.com/ingrammicro-xvantage/xi-sdk-resellers-python/archive/1.3.0.tar.gz
Project-URL: release-notes, https://github.com/ingrammicro-xvantage/xi-sdk-resellers-python/releases/
Keywords: xvantage,ingrammicro,resellerapi,xvantage integration
Classifier: Development Status :: 5 - Production/Stable
Classifier: Intended Audience :: Developers
Classifier: License :: OSI Approved :: MIT License
Classifier: Operating System :: OS Independent
Classifier: Programming Language :: Python :: 3
Classifier: Programming Language :: Python :: 3.8
Classifier: Programming Language :: Python :: 3.9
Classifier: Programming Language :: Python :: 3.10
Classifier: Programming Language :: Python :: 3.11
Classifier: Programming Language :: Python :: 3.12
Classifier: Programming Language :: Python :: 3.13
Classifier: Topic :: Software Development :: Libraries :: Python Modules
Classifier: Topic :: Internet :: WWW/HTTP
Requires-Python: >=3.8
License-File: LICENCE
Requires-Dist: urllib3<3.0.0,>=2.1.0
Requires-Dist: python-dateutil>=2.8.2
Requires-Dist: pydantic>=2
Requires-Dist: typing-extensions>=4.7.1
Dynamic: author
Dynamic: home-page
Dynamic: license-file
